regen-docs
setup.py
DevAuth.egg-info/PKG-INFO
DevAuth.egg-info/SOURCES.txt
DevAuth.egg-info/dependency_links.txt
DevAuth.egg-info/entry_points.txt
DevAuth.egg-info/not-zip-safe
DevAuth.egg-info/requires.txt
DevAuth.egg-info/top_level.txt
devauth/__init__.py
devauth/htpasswd.py
devauth/ip_denied.html
devauth/login.html
devauth/tests/__init__.py
devauth/tests/test_devauth.py
docs/code.txt
docs/conf.py
docs/index.txt
docs/license.txt
docs/news.txt