Metadata-Version: 1.0
Name: DevAuth
Version: 0.1.1
Summary: Authentication for developer access to applications
Home-page: http://devauth.openplans.org
Author: Ian Bicking
Author-email: ianb@openplans.org
License: MIT
Keywords: wsgi debug tool
Platform: UNKNOWN
Classifier: Development Status :: 4 - Beta
Classifier: Framework :: Paste
Classifier: License :: OSI Approved :: MIT License
Classifier: Topic :: Internet :: WWW/HTTP :: WSGI
Classifier: Topic :: Internet :: WWW/HTTP :: WSGI :: Middleware
